monopay/__init__.py
monopay/__main__.py
monopay/asyncmonopay.py
monopay/decorators/__init__.py
monopay/decorators/decorators.py
monopay/exceptions/__init__.py
monopay/exceptions/bad_request.py
monopay/exceptions/base_exception.py
monopay/exceptions/invalidated_token.py
monopay/instances/__init__.py
monopay/instances/instances.py
monopay/methods/__init__.py
monopay/methods/invoice.py
monopay/methods/merchant.py
monopay/methods/qr.py
monopay/methods/wallet.py
monopay/responses/__init__.py
monopay/responses/responses.py
monopay/utils/__init__.py
monopay/utils/builders.py
monopay/utils/is_exception.py
monopay/utils/to_camel_case.py
monopay/utils/webhook_authentication.py
monopay-0.0.6.dist-info/METADATA
monopay-0.0.6.dist-info/WHEEL
monopay-0.0.6.dist-info/RECORD
