Metadata-Version: 2.1
Name: monopay
Version: 0.0.6
Summary: Python Sync/Async library for work with Monobank acquiring api
License: MIT
Author: yeghorkikhai
Author-email: yeghorkikhai@gmail.com
Requires-Python: >=3.8,<4.0
Classifier: License :: OSI Approved :: MIT License
Classifier: Programming Language :: Python :: 3
Classifier: Programming Language :: Python :: 3.8
Classifier: Programming Language :: Python :: 3.9
Classifier: Programming Language :: Python :: 3.10
Classifier: Programming Language :: Python :: 3.11
